daa_music/__init__.py
daa_music/cli.py
daa_music/utils.py
daa_music-0.0.5.dist-info/licenses/LICENSE
daa_music-0.0.5.dist-info/METADATA
daa_music-0.0.5.dist-info/WHEEL
daa_music-0.0.5.dist-info/entry_points.txt
daa_music-0.0.5.dist-info/top_level.txt
daa_music-0.0.5.dist-info/RECORD
