Metadata-Version: 2.4
Name: daa_music
Version: 0.0.5
Summary: A music streaming cli.
Author-email: Klka <klka@duck.com>
License-Expression: MIT
Project-URL: Homepage, https://github.com/kamalkoranga/daamusic
Project-URL: Repository, https://github.com/kamalkoranga/daamusic
Keywords: music,cli,audio,tool
Classifier: Programming Language :: Python :: 3
Classifier: Operating System :: OS Independent
Classifier: Development Status :: 3 - Alpha
Classifier: Intended Audience :: End Users/Desktop
Classifier: Topic :: Multimedia :: Sound/Audio
Classifier: Topic :: Utilities
Classifier: Environment :: Console
Requires-Python: >=3.10
License-File: LICENSE
Requires-Dist: rich==14.0.0
Requires-Dist: yt-dlp==2025.3.31
Dynamic: license-file
